pipgui/__init__.py
pipgui/__main__.py
pipgui/refreshLists.py
pipgui/GUI/__init__.py
pipgui/GUI/installScreen.py
pipgui/GUI/progressScreen.py
pipgui/GUI/startScreen.py
pipgui/GUI/uninstallScreen.py
pipgui/GUI/updateScreen.py
pipgui/Package_Management/__init__.py
pipgui/Package_Management/installedList.py
pipgui/Package_Management/outdatedList.py
pipgui/Resource_Files/db.txt
pipgui/Resource_Files/genreFile.json
pipgui/Resource_Files/genreListFile.json
pipgui/Resource_Files/genreTagFile.json
pipgui/Resource_Files/googledev.png
pipgui/Resource_Files/outdatedPackageList.json
pipgui/Resource_Files/outdatedPackageList3.json
pipgui/Resource_Files/packageDictFile.json
pipgui/Resource_Files/packageList.json
pipgui/Resource_Files/packageList3.json
pipgui/Resource_Files/pypi.txt
pipgui/Scraping/__init__.py
pipgui/Scraping/genreList.py
pipgui/Scraping/githubFile.py
pipgui/Scraping/packageList.py
pipgui/Scraping/pypiList.py
pipgui-1.3.dist-info/LICENSE.txt
pipgui-1.3.dist-info/METADATA
pipgui-1.3.dist-info/WHEEL
pipgui-1.3.dist-info/entry_points.txt
pipgui-1.3.dist-info/top_level.txt
pipgui-1.3.dist-info/RECORD
