Metadata-Version: 2.1
Name: pipgui
Version: 1.3
Summary: This package is GUI based tool for installing pip packages in your environment.
Home-page: https://github.com/GDGVIT/pip-gui
Author: Ayush Priya, DSC-VIT
Author-email: ayushpriya10@gmail.com, dscvitvellore@gmail.com
License: UNKNOWN
Platform: UNKNOWN
Classifier: Development Status :: 4 - Beta
Classifier: License :: OSI Approved :: GNU General Public License v3 (GPLv3)
Classifier: Programming Language :: Python :: 3
Classifier: Programming Language :: Python :: 3 :: Only
Classifier: Programming Language :: Python :: 3.6
Classifier: Programming Language :: Python :: Implementation :: CPython
Requires-Python: >=3.4
Requires-Dist: beautifulsoup4
Requires-Dist: sip (==4.19.8)
Requires-Dist: PyQt5 (==5.10.1)
